wolfsoftware/github_extractor/__init__.py
wolfsoftware/github_extractor/addons.py
wolfsoftware/github_extractor/branches.py
wolfsoftware/github_extractor/constants.py
wolfsoftware/github_extractor/contributors.py
wolfsoftware/github_extractor/exceptions.py
wolfsoftware/github_extractor/filters.py
wolfsoftware/github_extractor/github.py
wolfsoftware/github_extractor/languages.py
wolfsoftware/github_extractor/members.py
wolfsoftware/github_extractor/organisations.py
wolfsoftware/github_extractor/releases.py
wolfsoftware/github_extractor/repositories.py
wolfsoftware/github_extractor/stubs.py
wolfsoftware/github_extractor/tags.py
wolfsoftware/github_extractor/token.py
wolfsoftware/github_extractor/topics.py
wolfsoftware/github_extractor/user.py
wolfsoftware/github_extractor/utils.py
wolfsoftware/github_extractor/workflows.py
wolfsoftware.github_extractor-0.1.1.dist-info/LICENSE.md
wolfsoftware.github_extractor-0.1.1.dist-info/METADATA
wolfsoftware.github_extractor-0.1.1.dist-info/WHEEL
wolfsoftware.github_extractor-0.1.1.dist-info/top_level.txt
wolfsoftware.github_extractor-0.1.1.dist-info/RECORD
